CyberOsint/__init__.py
CyberOsint/main.py
CyberOsint-0.4.dist-info/METADATA
CyberOsint-0.4.dist-info/WHEEL
CyberOsint-0.4.dist-info/entry_points.txt
CyberOsint-0.4.dist-info/top_level.txt
CyberOsint-0.4.dist-info/RECORD
