Metadata-Version: 2.1
Name: CyberOsint
Version: 0.4
Summary: A tool for OSINT
Home-page: https://github.com/TheCyberStalker/CyberOsint
Author: Luka
Author-email: thecyberstalker@gmail.com
License: UNKNOWN
Platform: UNKNOWN
Classifier: Programming Language :: Python :: 3
Classifier: License :: OSI Approved :: MIT License
Classifier: Operating System :: OS Independent
Requires-Dist: pytelegrambotapi
Requires-Dist: requests
Requires-Dist: colorama
Requires-Dist: faker
